metacraft/__init__.py
metacraft/core.py
metacraft-2025.10.6.dist-info/licenses/LICENSE
metacraft-2025.10.6.dist-info/METADATA
metacraft-2025.10.6.dist-info/WHEEL
metacraft-2025.10.6.dist-info/top_level.txt
metacraft-2025.10.6.dist-info/RECORD
