Metadata-Version: 2.4
Name: MetaCraft
Version: 2025.10.6
Summary: Toolkit to enrich, validate and explore YAML metadata from a pandas DataFrame.
Author: Jose Carlos Del Valle
License: MIT
Project-URL: Homepage, https://example.com/MetaCraft
Requires-Python: >=3.8
License-File: LICENSE
Requires-Dist: numpy>=1.23
Requires-Dist: pandas>=2.1
Requires-Dist: PyYAML>=6.0
Requires-Dist: openai>=1.14
Requires-Dist: tdigest==0.5.2.2
Requires-Dist: datasketch>=1.5
Dynamic: license-file
Dynamic: requires-python
